ftllexbuffer/__init__.py
ftllexbuffer/deprecation.py
ftllexbuffer/enums.py
ftllexbuffer/introspection.py
ftllexbuffer/locale_utils.py
ftllexbuffer/localization.py
ftllexbuffer/py.typed
ftllexbuffer/analysis/__init__.py
ftllexbuffer/analysis/graph.py
ftllexbuffer/diagnostics/__init__.py
ftllexbuffer/diagnostics/codes.py
ftllexbuffer/diagnostics/errors.py
ftllexbuffer/diagnostics/templates.py
ftllexbuffer/diagnostics/validation.py
ftllexbuffer/parsing/__init__.py
ftllexbuffer/parsing/currency.py
ftllexbuffer/parsing/dates.py
ftllexbuffer/parsing/guards.py
ftllexbuffer/parsing/numbers.py
ftllexbuffer/runtime/__init__.py
ftllexbuffer/runtime/bundle.py
ftllexbuffer/runtime/cache.py
ftllexbuffer/runtime/function_bridge.py
ftllexbuffer/runtime/function_metadata.py
ftllexbuffer/runtime/functions.py
ftllexbuffer/runtime/locale_context.py
ftllexbuffer/runtime/plural_rules.py
ftllexbuffer/runtime/resolver.py
ftllexbuffer/syntax/__init__.py
ftllexbuffer/syntax/ast.py
ftllexbuffer/syntax/cursor.py
ftllexbuffer/syntax/position.py
ftllexbuffer/syntax/serializer.py
ftllexbuffer/syntax/validator.py
ftllexbuffer/syntax/visitor.py
ftllexbuffer/syntax/parser/__init__.py
ftllexbuffer/syntax/parser/core.py
ftllexbuffer/syntax/parser/entries.py
ftllexbuffer/syntax/parser/expressions.py
ftllexbuffer/syntax/parser/patterns.py
ftllexbuffer/syntax/parser/primitives.py
ftllexbuffer/syntax/parser/whitespace.py
ftllexbuffer/validation/__init__.py
ftllexbuffer/validation/resource.py
ftllexbuffer-0.21.0.dist-info/METADATA
ftllexbuffer-0.21.0.dist-info/WHEEL
ftllexbuffer-0.21.0.dist-info/licenses/LICENSE
ftllexbuffer-0.21.0.dist-info/licenses/NOTICE
ftllexbuffer-0.21.0.dist-info/RECORD
