Metadata-Version: 2.4
Name: ftllexbuffer
Version: 0.21.0
Summary: Python implementation of the FTL (Fluent Translation List) specification
Project-URL: Homepage, https://github.com/resoltico/ftllexbuffer
Project-URL: Documentation, https://github.com/resoltico/ftllexbuffer#readme
Project-URL: Repository, https://github.com/resoltico/ftllexbuffer.git
Project-URL: Issues, https://github.com/resoltico/ftllexbuffer/issues
Project-URL: Changelog, https://github.com/resoltico/ftllexbuffer/blob/main/CHANGELOG.md
Author: Ervins Strauhmanis
License: MIT
License-File: LICENSE
License-File: NOTICE
Keywords: cldr,fluent,ftl,i18n,internationalization,l10n,localization,plurals,translation
Classifier: Development Status :: 3 - Alpha
Classifier: Intended Audience :: Developers
Classifier: License :: OSI Approved :: MIT License
Classifier: Operating System :: OS Independent
Classifier: Programming Language :: Python :: 3
Classifier: Programming Language :: Python :: 3 :: Only
Classifier: Programming Language :: Python :: 3.13
Classifier: Programming Language :: Python :: 3.14
Classifier: Topic :: Software Development :: Internationalization
Classifier: Topic :: Software Development :: Localization
Classifier: Typing :: Typed
Requires-Python: >=3.13
Requires-Dist: babel<3.0.0,>=2.17.0
Provides-Extra: dev
Requires-Dist: hypothesis>=6.148.7; extra == 'dev'
Requires-Dist: mypy>=1.19.1; extra == 'dev'
Requires-Dist: pylint>=4.0.4; extra == 'dev'
Requires-Dist: pytest-benchmark>=5.2.3; extra == 'dev'
Requires-Dist: pytest-cov>=7.0.0; extra == 'dev'
Requires-Dist: pytest>=9.0.2; extra == 'dev'
Requires-Dist: ruff>=0.14.9; extra == 'dev'
Provides-Extra: publish
Requires-Dist: build>=1.3.0; extra == 'publish'
Requires-Dist: twine>=6.2.0; extra == 'publish'
